robotpy_websim/__init__.py
robotpy_websim/fake_time.py
robotpy_websim/sim_server.py
robotpy_websim/version.py
robotpy_websim/html/dist/3cf97837524dd7445e9d1462e3c4afe2.woff
robotpy_websim/html/dist/47151e87c5a8666791a91007de4962da.eot
robotpy_websim/html/dist/49be7e7613c17e9c9fd9.worker.js
robotpy_websim/html/dist/527eff645d8ead16666afb6931041279.otf
robotpy_websim/html/dist/93cc7aa654ae36b0828716f5ec3159cd.ttf
robotpy_websim/html/dist/analog.bundle.js
robotpy_websim/html/dist/app.bundle.js
robotpy_websim/html/dist/auto-chooser.bundle.js
robotpy_websim/html/dist/can.bundle.js
robotpy_websim/html/dist/control.bundle.js
robotpy_websim/html/dist/digital.bundle.js
robotpy_websim/html/dist/encoder.bundle.js
robotpy_websim/html/dist/field.bundle.js
robotpy_websim/html/dist/game-data.bundle.js
robotpy_websim/html/dist/gyro.bundle.js
robotpy_websim/html/dist/index.html
robotpy_websim/html/dist/joystick.bundle.js
robotpy_websim/html/dist/solenoid.bundle.js
robotpy_websim/html/dist/tableviewer.bundle.js
robotpy_websim/html/dist/time.bundle.js
robotpy_websim/html/dist/assets/media/open-iconic.svg
robotpy_websim-2019.0.0a5.dist-info/METADATA
robotpy_websim-2019.0.0a5.dist-info/WHEEL
robotpy_websim-2019.0.0a5.dist-info/entry_points.txt
robotpy_websim-2019.0.0a5.dist-info/top_level.txt
robotpy_websim-2019.0.0a5.dist-info/RECORD
