Metadata-Version: 2.1
Name: robotpy-websim
Version: 2019.0.0a5
Summary: RobotPy web-based low fidelity FRC robot simulation package
Home-page: https://github.com/robotpy/robotpy-websim
Author: Amory Galili, Dustin Spicuzza
Author-email: robotpy@googlegroups.com
License: BSD License
Keywords: frc first robotics simulation
Platform: UNKNOWN
Classifier: Development Status :: 4 - Beta
Classifier: Intended Audience :: Developers
Classifier: Intended Audience :: Education
Classifier: License :: OSI Approved :: BSD License
Classifier: Operating System :: OS Independent
Classifier: Programming Language :: Python :: 3.4
Classifier: Topic :: Scientific/Engineering
Requires-Dist: tornado (>=5.0.2)
Requires-Dist: pyfrc (<2020.0.0,>=2019.0.0)
Requires-Dist: wpilib (<2020.0.0,>=2019.0.0)
Requires-Dist: robotpy-hal-sim (<2020.0.0,>=2019.0.0)
Requires-Dist: pynetworktables (>=2019.0.0)
Requires-Dist: pynetworktables2js (>=2019.0.0)
